README.md
setup.py
kong_oauth/__init__.py
kong_oauth/admin.py
kong_oauth/apps.py
kong_oauth/authbackends.py
kong_oauth/drf_authbackends.py
kong_oauth/helpers.py
kong_oauth/kong.py
kong_oauth/middleware.py
kong_oauth/models.py
kong_oauth/resource.py
kong_oauth/testutils.py
kong_oauth/urls.py
kong_oauth/views.py
kong_oauth.egg-info/PKG-INFO
kong_oauth.egg-info/SOURCES.txt
kong_oauth.egg-info/dependency_links.txt
kong_oauth.egg-info/not-zip-safe
kong_oauth.egg-info/top_level.txt